Workbook

Sheet Cost-Benefit Analysis
A1: Parameter | B1: Assumption Value
A2: Discount Rate | B2: 0.065
A3: Number of DC chargers_Bus | B3: 5
A4: Number of DC chargers_Taxi | B4: 10
A5: Number of AC chargers | B5: 50
A6: Number of Taxi | B6: 100
A7: Number of Bus | B7: 10
A9: 1. Net Present Value(NPV) Table_Baseline (100% EV Participation)
A10: Component | B10: Description | C10: Year 0 (SGD) | D10: Year 1 (SGD) | E10: Year 2 (SGD) | F10: Year 3 (SGD) | G10: Year 4 (SGD) | H10: Year 5 (SGD) | I10: Year 6 (SGD) | J10: Year 7 (SGD) | K10: Year 8 (SGD) | L10: Year 9 (SGD) | M10: Year 10 (SGD)
A11: Incremental CAPEX
A12: (-) DC | B12: Hardware premium + Compliance/Install | C12: =CAPEX!E3*SUM(B3:B4) -> 270000
A13: (-) AC | B13: Hardware premium + Compliance/Install | C13: =CAPEX!E4*B5 -> 225000
A14: Total CAPEX | C14: =SUM(C12:C13) -> 495000
A15: Gross Revenue Streams
A16: (+) Arbitrage (Power constrained) | B16: Limited to 7kW discharge to preserve SoH. | D16: =Revenue!$H$6 -> 15731.1 | E16: =Revenue!$H$6 -> 15731.1 | F16: =Revenue!$H$6 -> 15731.1 | G16: =Revenue!$H$6 -> 15731.1 | H16: =Revenue!$H$6 -> 15731.1 | I16: =Revenue!$H$6 -> 15731.1 | J16: =Revenue!$H$6 -> 15731.1 | K16: =Revenue!$H$6 -> 15731.1 | ... M16: =Revenue!$H$6 -> 15731.1
A17: (+) Contingency Reserve | B17: Passive availability payment (Zero battery wear). | D17: =Revenue!$I$6 -> 72334.08 | E17: =Revenue!$I$6 -> 72334.08 | F17: =Revenue!$I$6 -> 72334.08 | G17: =Revenue!$I$6 -> 72334.08 | H17: =Revenue!$I$6 -> 72334.08 | I17: =Revenue!$I$6 -> 72334.08 | J17: =Revenue!$I$6 -> 72334.08 | K17: =Revenue!$I$6 -> 72334.08 | ... M17: =Revenue!$I$6 -> 72334.08
A18: (+) Demand Response (DR) | B18: High-value grid stress relief (20 events/year). | D18: =Revenue!$J$6 -> 56929.6 | E18: =Revenue!$J$6 -> 56929.6 | F18: =Revenue!$J$6 -> 56929.6 | G18: =Revenue!$J$6 -> 56929.6 | H18: =Revenue!$J$6 -> 56929.6 | I18: =Revenue!$J$6 -> 56929.6 | J18: =Revenue!$J$6 -> 56929.6 | K18: =Revenue!$J$6 -> 56929.6 | ... M18: =Revenue!$J$6 -> 56929.6
A19: Total Revenue | D19: =SUM(D16:D18) -> 144994.78 | E19: =SUM(E16:E18) -> 144994.78 | F19: =SUM(F16:F18) -> 144994.78 | G19: =SUM(G16:G18) -> 144994.78 | H19: =SUM(H16:H18) -> 144994.78 | I19: =SUM(I16:I18) -> 144994.78 | J19: =SUM(J16:J18) -> 144994.78 | K19: =SUM(K16:K18) -> 144994.78 | ... M19: =SUM(M16:M18) -> 144994.78
A20: Operational Expenditures
A21: (-) Software & Aggregation | B21: SaaS fees for market participation. | D21: =OPEX!$E$6 -> 38500 | E21: =OPEX!$E$6 -> 38500 | F21: =OPEX!$E$6 -> 38500 | G21: =OPEX!$E$6 -> 38500 | H21: =OPEX!$E$6 -> 38500 | I21: =OPEX!$E$6 -> 38500 | J21: =OPEX!$E$6 -> 38500 | K21: =OPEX!$E$6 -> 38500 | ... M21: =OPEX!$E$6 -> 38500
A22: (-) Battery Wear Cost | B22: 3,000 kWh discharge at $0.05/kWh. | D22: =OPEX!$H$6 -> 17147.6 | E22: =OPEX!$H$6 -> 17147.6 | F22: =OPEX!$H$6 -> 17147.6 | G22: =OPEX!$H$6 -> 17147.6 | H22: =OPEX!$H$6 -> 17147.6 | I22: =OPEX!$H$6 -> 17147.6 | J22: =OPEX!$H$6 -> 17147.6 | K22: =OPEX!$H$6 -> 17147.6 | ... M22: =OPEX!$H$6 -> 17147.6
A23: (-) Incremental Maintenance | B23: Inverter checks and cybersecurity patches. | D23: =OPEX!$J$6 -> 6000 | E23: =OPEX!$J$6 -> 6000 | F23: =OPEX!$J$6 -> 6000 | G23: =OPEX!$J$6 -> 6000 | H23: =OPEX!$J$6 -> 6000 | I23: =OPEX!$J$6 -> 6000 | J23: =OPEX!$J$6 -> 6000 | K23: =OPEX!$J$6 -> 6000 | ... M23: =OPEX!$J$6 -> 6000
A24: Total OPEX | D24: =SUM(D21:D23) -> 61647.6 | E24: =SUM(E21:E23) -> 61647.6 | F24: =SUM(F21:F23) -> 61647.6 | G24: =SUM(G21:G23) -> 61647.6 | H24: =SUM(H21:H23) -> 61647.6 | I24: =SUM(I21:I23) -> 61647.6 | J24: =SUM(J21:J23) -> 61647.6 | K24: =SUM(K21:K23) -> 61647.6 | ... M24: =SUM(M21:M23) -> 61647.6
A25: Net Operational Income | B25: Annual Cash Flow | D25: =D19-D24 -> 83347.18 | E25: =E19-E24 -> 83347.18 | F25: =F19-F24 -> 83347.18 | G25: =G19-G24 -> 83347.18 | H25: =H19-H24 -> 83347.18 | I25: =I19-I24 -> 83347.18 | J25: =J19-J24 -> 83347.18 | K25: =K19-K24 -> 83347.18 | ... M25: =M19-M24 -> 83347.18
A26: Discounted CF | B26: Discounted Cash Flow | D26: =D25/(1+$B$2)^1 -> 78260.263 | E26: =E25/(1+$B$2)^2 -> 73483.815 | F26: =F25/(1+$B$2)^3 -> 68998.887 | G26: =G25/(1+$B$2)^4 -> 64787.688 | H26: =H25/(1+$B$2)^5 -> 60833.509 | I26: =I25/(1+$B$2)^6 -> 57120.666 | J26: =J25/(1+$B$2)^7 -> 53634.428 | K26: =K25/(1+$B$2)^8 -> 50360.966 | L26: =L25/(1+$B$2)^9 -> 47287.292 | M26: =M25/(1+$B$2)^10 -> 44401.213
A27: Net Present Value(NPV) | B27: NPV = PV(Revenue) - PV(CAPEX) | C27: =-C14 -> -495000 | D27: =SUM($C$27,$D$26:D26) -> -416739.74 | E27: =SUM($C$27,$D$26:E26) -> -343255.92 | F27: =SUM($C$27,$D$26:F26) -> -274257.03 | G27: =SUM($C$27,$D$26:G26) -> -209469.35 | H27: =SUM($C$27,$D$26:H26) -> -148635.84 | I27: =SUM($C$27,$D$26:I26) -> -91515.172 | J27: =SUM($C$27,$D$26:J26) -> -37880.743 | K27: =SUM($C$27,$D$26:K26) -> 12480.222 | ... M27: =SUM($C$27,$D$26:M26) -> 104168.73
A29: 2.Return of Investment (ROI)
A30: Name | B30: Initial Investment | C30: Annual CF | D30: Project Time | E30: Total Net Profit | F30: Result
A31: ROI | B31: =C14 -> 495000 | C31: =D25 -> 83347.18 | D31: 10 | E31: =C31*D31-B31 -> 338471.8 | F31: =E31/B31*100% -> 0.68378141
A33: 3. Internal Rate of Return (IRR)
A34: Name | B34: Result
A35: IRR | B35: =10.7997% -> 0.107997
A37: 4. Payback Period
A38: Payback Period Type | B38: Explain | C38: No. of Years
A39: Static Payback Period | B39: T_static = Initial Investment / Net CF It does not consider the factor of discounted rate | C39: =$C$14/$D$25 -> 5.9390132
A40: Dynamic Payback Period | B40: The number of years the cumulative discounted cash flow covers the initial investment | C40: =7+(-J27/K26) -> 7.7521846

Sheet Revenue
A1: Annual Revenue Table
A2: Case | B2: Charger Capacity (kW) | C2: No. of Chargers | D2: No. of Vehicles | E2: Arbitrage Revenue per Vehicle (SGD) | F2: Ancillary Contingency Reserve per Vehicle (SGD) | G2: DR Incentives per Vehicle (SGD) | H2: Total Arbitrage Revenue (SGD) | I2: Total Ancillary Contingency Reserve (SGD) | J2: Total DR Incentives (SGD) | K2: Total Annual Revenue
A3: 10 Bus + 5 DC | B3: 60 | C3: 5 | D3: 10 | E3: ='Revenue-Arbitrage'!G3 -> 368.35 | F3: ='Revenue-Ancilary Service'!H3 -> 1814.4 | G3: ='Revenue-DR'!I3 -> 1428 | H3: =D3*'Revenue-Arbitrage'!G3 -> 3683.5 | I3: =D3*'Revenue-Ancilary Service'!$H$3 -> 18144 | J3: =D3*'Revenue-DR'!I3 -> 14280 | K3: =SUM(H3:J3) -> 36107.5
A4: 20 Taxi + 10 DC | B4: 60 | C4: 10 | D4: 20 | E4: ='Revenue-Arbitrage'!G5 -> 398.98 | F4: ='Revenue-Ancilary Service'!H3 -> 1814.4 | G4: ='Revenue-DR'!I3 -> 1428 | H4: =D4*'Revenue-Arbitrage'!G5 -> 7979.6 | I4: =D4*'Revenue-Ancilary Service'!$H$3 -> 36288 | J4: =D4*'Revenue-DR'!I3 -> 28560 | K4: =SUM(H4:J4) -> 72827.6
A5: 80 Taxi + 50 AC | B5: 7.4 | C5: 50 | D5: 80 | E5: ='Revenue-Arbitrage'!G7 -> 50.85 | F5: ='Revenue-Ancilary Service'!H4 -> 223.776 | G5: ='Revenue-DR'!I4 -> 176.12 | H5: =D5*'Revenue-Arbitrage'!G7 -> 4068 | I5: =D5*'Revenue-Ancilary Service'!H4 -> 17902.08 | J5: =D5*'Revenue-DR'!I4 -> 14089.6 | K5: =SUM(H5:J5) -> 36059.68
A6: 100% Participation (Baseline) | H6: =SUM(H3:H5) -> 15731.1 | I6: =SUM(I3:I5) -> 72334.08 | J6: =SUM(J3:J5) -> 56929.6 | K6: =SUM(H6:J6) -> 144994.78
A7: 50% Participation | H7: =H6*50% -> 7865.55 | I7: =I6*50% -> 36167.04 | J7: =J6*50% -> 28464.8 | K7: =SUM(H7:J7) -> 72497.39

Sheet Revenue-Arbitrage
A1: Arbitrage Revenue per EV
A2: Case | B2: Fleet Type | C2: Strategy | D2: Charger Type | E2: Price Spread (SGD/kWh) | F2: Daily Est. Revenue (SGD) | G2: Annually Est. Revenue (SGD) | H2: Note | I2: Recommendation
A3: Case A | B3: AM Bus | C3: Arbitrage | D3: DC | E3: 0.067 | F3: 1.05 | G3: 368.35 | H3: Generate Arbitrage Revenue | I3: Recommed
A4: Case B | B4: PM/Full-Day Bus | C4: Cost Saving | D4: DC | E4: 0.0013 | F4: 0.25 | G4: 88.59 | H4: Reduce OPEX
A5: Case C-1 | B5: Taxi | C5: Cost Saving | D5: DC | E5: 0.0307 | F5: 1.14 | G5: 398.98 | H5: Reduce OPEX | I5: Recommed
A6: Case C-2 | B6: Taxi | C6: Arbitrage | D6: DC | E6: 0.0701 | F6: 0.17 | G6: 61.57 | H6: Need DC 60kW to support arbitrage
A7: Case D | B7: Taxi | C7: Arbitrage | D7: AC | E7: 0.0185 | F7: 0.15 | G7: 50.85 | H7: Need DC 60kW to support arbitrage | I7: Recommed

Sheet Revenue-Ancilary Service
A1: Ancillary Service Revenue per EV
A2: Case | B2: Charger Type | C2: Annual Operational Days | D2: Committed Curtailable Capacity (MW) | E2: Daily Availability Window (h) | F2: Market Clearing Price (SGD/MWh) | G2: System Reliability Factor | H2: Annual Revenue/vehicle (SGD)
A3: A | B3: DC 60kW | C3: 350 | D3: =60/1000 -> 0.06 | E3: 6 | F3: 15 | G3: 0.96 | H3: =C3*D3*E3*F3*G3 -> 1814.4
A4: B | B4: AC 7.4kW | C4: 350 | D4: =7.4/1000 -> 0.0074 | E4: 6 | F4: 15 | G4: 0.96 | H4: =C4*D4*E4*F4*G4 -> 223.776

Sheet Revenue-DR
A1: Demand Response Incentives per EV
A2: Case | B2: Fleet Type | C2: Charger Type (kW) | D2: DR Event Time(h) | E2: DR Incentives (SGD/kWh) | F2: Success Rate | G2: No. of DR Event | H2: Annual Est. Revenue/vehicle /event (SGD) | I2: Annual Est. Revenue (SGD)
A3: DR-DC | B3: Bus & Taxi | C3: 60 | D3: 0.5 | E3: 2.8 | F3: 0.85 | G3: 20 | H3: =C3*D3*E3*F3 -> 71.4 | I3: =G3*H3 -> 1428
A4: DR-AC | B4: Taxi | C4: 7.4 | D4: 0.5 | E4: 2.8 | F4: 0.85 | G4: 20 | H4: =C4*D4*E4*F4 -> 8.806 | I4: =G4*H4 -> 176.12

Sheet CAPEX
A1: Annual CAPEX Table
A2: Charger Type | B2: Standard Charger Price (SGD) | C2: Hardware Premium (SGD) | D2: Installation Fee (SGD) | E2: Total CAPEX / Charger(SGD)
A3: DC 60kW | B3: 20000 | C3: =B3*50% -> 10000 | D3: =C3*80% -> 8000 | E3: =SUM(C3:D3) -> 18000
A4: AC 7.4kW | B4: 1500 | C4: =4000-1500 -> 2500 | D4: =C4*80% -> 2000 | E4: =SUM(C4:D4) -> 4500
A5: Total CAPEX | E5: =SUM(E3:E4) -> 22500

Sheet OPEX
A1: Annual OPEX Model
A2: Case | B2: No. of EV | C2: No. of Chargers | D2: Software License/Vehicle (SGD) | E2: Software License (SGD) | F2: Capacity (kWh) | G2: Unit Wear Cost (SGD/kWh) | H2: Annual Wear Cost (SGD) | I2: Unit Maintenance Cost(SGD) | J2: Maintenance Cost (SGD) | K2: Total Annual OPEX (SGD)
A3: 10 Bus + 5 DC | B3: 10 | C3: 5 | D3: 350 | E3: =B3*D3 -> 3500 | F3: =7*3*350+60*0.5*20 -> 7950 | G3: 0.05 | H3: =B3*F3*G3 -> 3975 | I3: 200 | J3: =C3*I3 -> 1000 | K3: =SUM(E3,H3,I3) -> 7675
A4: 20 Taxi + 10 DC | B4: 20 | C4: 10 | D4: 350 | E4: =B4*D4 -> 7000 | F4: =7*1.5*350+50*0.5*20 -> 4175 | G4: 0.05 | H4: =B4*F4*G4 -> 4175 | I4: 200 | J4: =C4*I4 -> 2000 | K4: =SUM(E4,H4,I4) -> 11375
A5: 80 Taxi + 50 AC | B5: 80 | C5: 50 | D5: 350 | E5: =B5*D5 -> 28000 | F5: =7*1.5*350+7.4*0.5*20 -> 3749 | G5: =0.05*60% -> 0.03 | H5: =B5*F5*G5 -> 8997.6 | I5: 60 | J5: =C5*I5 -> 3000 | K5: =SUM(E5,H5,I5) -> 37057.6
A6: Sum | E6: =SUM(E3:E5) -> 38500 | H6: =SUM(H3:H5) -> 17147.6 | J6: =SUM(J3:J5) -> 6000 | K6: =SUM(E6,H6,J6) -> 61647.6
